setup.py
flask_bundle_system.egg-info/PKG-INFO
flask_bundle_system.egg-info/SOURCES.txt
flask_bundle_system.egg-info/dependency_links.txt
flask_bundle_system.egg-info/not-zip-safe
flask_bundle_system.egg-info/requires.txt
flask_bundle_system.egg-info/top_level.txt
flask_bundlesystem/__init__.py
flask_bundlesystem/bundle_system.py