Metadata-Version: 1.1
Name: flask-bundle-system
Version: 0.1
Summary: Flask extension for work with blueprints as bundles
Home-page: https://github.com/yograterol/flask-bundle-system
Author: yograterol
Author-email: yograterol@fedoraproject.org
License: BSD
Platform: any
Classifier: Development Status :: 4 - Beta
Classifier: Environment :: Web Environment
Classifier: Intended Audience :: Developers
Classifier: License :: OSI Approved :: BSD License
Classifier: Operating System :: OS Independent
Classifier: Programming Language :: Python
Classifier: Topic :: Internet :: WWW/HTTP :: Dynamic Content
Classifier: Topic :: Software Development :: Libraries :: Python Modules
